{"title":"[PeterNorth] - Tight Teen Brats XXX 2018 WEB-DL mp4","magnet":"magnet:?xt=urn:btih:0191637321f536d4688788dbdb1bc9e7d6896658&dn=%5BPeterNorth%5D+-+Tight+Teen+Brats+XXX+2018+WEB-DL+mp4&tr=udp%3A%2F%2Ftracker.leechers-paradise.org%3A6969&tr=udp%3A%2F%2Fzer0day.ch%3A1337&tr=udp%3A%2F%2Fopen.demonii.com%3A1337&tr=udp%3A%2F%2Ftracker.coppersurfer.tk%3A6969&tr=udp%3A%2F%2Fexodus.desync.com%3A6969","uploader":"NewPornUp","categoryP":"porn","categoryS":"movies","size":"825450765","seeders":"10","leechers":"21","description":"[PeterNorth] - Tight Teen Brats XXX 2018 WEB-DL mp4\r\n\r\nScreenshots :\r\n <a href=\"\nhttp://imggo.xyz/img-u/2018/5b0655a97455a.jpeg.html\" rel=\"nofollow\" target=\"_NEW\">\nhttp://imggo.xyz/img-u/2018/5b0655a97455a.jpeg.html</a>\r\n <a href=\"\nhttp://imggo.xyz/img-u/2018/5b0655a974749.jpeg.html\" rel=\"nofollow\" target=\"_NEW\">\nhttp://imggo.xyz/img-u/2018/5b0655a974749.jpeg.html</a>","last_updated":"2018-05-24T12:10:01.690Z","parsed":{"xt":"urn:btih:0191637321f536d4688788dbdb1bc9e7d6896658","dn":"[PeterNorth] - Tight Teen Brats XXX 2018 WEB-DL mp4","tr":["udp://exodus.desync.com:6969","udp://open.demonii.com:1337","udp://tracker.coppersurfer.tk:6969","udp://tracker.leechers-paradise.org:6969","udp://zer0day.ch:1337"],"infoHash":"0191637321f536d4688788dbdb1bc9e7d6896658","infoHashBuffer":{"type":"Buffer","data":[1,145,99,115,33,245,54,212,104,135,136,219,219,27,201,231,214,137,102,88]},"name":"[PeterNorth] - Tight Teen Brats XXX 2018 WEB-DL mp4","announce":["udp://exodus.desync.com:6969","udp://open.demonii.com:1337","udp://tracker.coppersurfer.tk:6969","udp://tracker.leechers-paradise.org:6969","udp://zer0day.ch:1337"],"urlList":[]}}