{"title":"Colette G - Ass Fuck The Slut (2018-05-23, Anal, All Sex, Blowjo","magnet":"magnet:?xt=urn:btih:0dc634d2035dbdda6e760820911be2afd48c3f59&dn=Colette+G+-+Ass+Fuck+The+Slut+%282018-05-23%2C+Anal%2C+All+Sex%2C+Blowjo&tr=udp%3A%2F%2Ftracker.leechers-paradise.org%3A6969&tr=udp%3A%2F%2Fzer0day.ch%3A1337&tr=udp%3A%2F%2Fopen.demonii.com%3A1337&tr=udp%3A%2F%2Ftracker.coppersurfer.tk%3A6969&tr=udp%3A%2F%2Fexodus.desync.com%3A6969","uploader":"NewPornUp","categoryP":"porn","categoryS":"hd___movies","size":"784116346","seeders":"9","leechers":"5","description":"Colette G - Ass Fuck The Slut (2018-05-23, Anal, All Sex, Blowjob, 720p]","last_updated":"2018-05-24T12:08:17.303Z","parsed":{"xt":"urn:btih:0dc634d2035dbdda6e760820911be2afd48c3f59","dn":"Colette G - Ass Fuck The Slut (2018-05-23, Anal, All Sex, Blowjo","tr":["udp://exodus.desync.com:6969","udp://open.demonii.com:1337","udp://tracker.coppersurfer.tk:6969","udp://tracker.leechers-paradise.org:6969","udp://zer0day.ch:1337"],"infoHash":"0dc634d2035dbdda6e760820911be2afd48c3f59","infoHashBuffer":{"type":"Buffer","data":[13,198,52,210,3,93,189,218,110,118,8,32,145,27,226,175,212,140,63,89]},"name":"Colette G - Ass Fuck The Slut (2018-05-23, Anal, All Sex, Blowjo","announce":["udp://exodus.desync.com:6969","udp://open.demonii.com:1337","udp://tracker.coppersurfer.tk:6969","udp://tracker.leechers-paradise.org:6969","udp://zer0day.ch:1337"],"urlList":[]}}