{"title":"Couple Fucks Pigtailed Freckle Faced Redhead Teen.mp4","magnet":"magnet:?xt=urn:btih:197d3e8e5ab991e683854fb21308c9d7239545e8&dn=Couple+Fucks+Pigtailed+Freckle+Faced+Redhead+Teen.mp4&tr=udp%3A%2F%2Ftracker.leechers-paradise.org%3A6969&tr=udp%3A%2F%2Fzer0day.ch%3A1337&tr=udp%3A%2F%2Fopen.demonii.com%3A1337&tr=udp%3A%2F%2Ftracker.coppersurfer.tk%3A6969&tr=udp%3A%2F%2Fexodus.desync.com%3A6969","uploader":"demonoidt","categoryP":"porn","categoryS":"movie_clips","size":"92459887","seeders":"1","leechers":"0","description":"Samples\r\n <a href=\"\nhttp://wallpaperspic.pw/couple-fucks-pigtailed-freckle-faced-redhead-teen/\" rel=\"nofollow\" target=\"_NEW\">\nhttp://wallpaperspic.pw/couple-fucks-pigtailed-freckle-faced-redhead-teen/</a>\r\n <a href=\"\nhttp://pornweb.xyz/2018/07/02/couple-fucks-pigtailed-freckle-faced-redhead-teen/\" rel=\"nofollow\" target=\"_NEW\">\nhttp://pornweb.xyz/2018/07/02/couple-fucks-pigtailed-freckle-faced-redhead-teen/</a>","last_updated":"2018-07-02T12:01:37.297Z","parsed":{"xt":"urn:btih:197d3e8e5ab991e683854fb21308c9d7239545e8","dn":"Couple Fucks Pigtailed Freckle Faced Redhead Teen.mp4","tr":["udp://exodus.desync.com:6969","udp://open.demonii.com:1337","udp://tracker.coppersurfer.tk:6969","udp://tracker.leechers-paradise.org:6969","udp://zer0day.ch:1337"],"infoHash":"197d3e8e5ab991e683854fb21308c9d7239545e8","infoHashBuffer":{"type":"Buffer","data":[25,125,62,142,90,185,145,230,131,133,79,178,19,8,201,215,35,149,69,232]},"name":"Couple Fucks Pigtailed Freckle Faced Redhead Teen.mp4","announce":["udp://exodus.desync.com:6969","udp://open.demonii.com:1337","udp://tracker.coppersurfer.tk:6969","udp://tracker.leechers-paradise.org:6969","udp://zer0day.ch:1337"],"urlList":[]}}