{"title":"Elementary.S06E17.1080p.WEB.x264-TBS[TGx]","magnet":"magnet:?xt=urn:btih:1f77b1b8fee2fcf384063e206bd1dca2fb05749a&dn=Elementary.S06E17.1080p.WEB.x264-TBS%5BTGx%5D&tr=udp%3A%2F%2Ftracker.leechers-paradise.org%3A6969&tr=udp%3A%2F%2Fzer0day.ch%3A1337&tr=udp%3A%2F%2Fopen.demonii.com%3A1337&tr=udp%3A%2F%2Ftracker.coppersurfer.tk%3A6969&tr=udp%3A%2F%2Fexodus.desync.com%3A6969","uploader":"sotnikam","categoryP":"video","categoryS":"hd___tv_shows","size":"1491897291","seeders":"25","leechers":"31","description":"Elementary.S06E17.1080p.WEB.x264-TBS[TGx] <a href=\" https://www.imdb.com/title/tt2191671\" rel=\"nofollow\" target=\"_NEW\"> https://www.imdb.com/title/tt2191671</a>\n \n -----------------------------------------\n SERIES INFO\n Genre: Crime Drama Mystery\n Stars: Jonny Lee Miller, Aidan Quinn, Jon Michael Hill, Lucy Liu, John Noble\n \n -----------------------------------------\n EPISODE INFO\n Title: The Worms Crawl In, The Worms Crawl Out\n Airdate: 2018-08-20\n Episode plot: Holmes and Watson investigate multiple motives for murder when a zoologist is killed because of his numerous love affairs or his trailblazing research. Also, Holmes finds himself the victim of identity theft after his medical records are stolen.\n \n -----------------------------------------\n MEDIAINFO\n Container = Matroska (mkv)\n Duration = 00:42:53.028\n Filesize = 1 GiB\n --Video\n Codec info = AVC High@L4 | V_MPEG4/ISO/AVC\n Resolution = 1920x1080\n Display AR = 1.778 | 16:9\n Bitrate = 4 500 kb/s\n Encoder = x264 - core 152\n --Audio\n Codec info = AAC LC | A_AAC\n Channels = 2\n \n -----------------------------------------\n SCREENS\n  <a href=\" https://imgmak.com/image/gVT\" rel=\"nofollow\" target=\"_NEW\"> https://imgmak.com/image/gVT</a>\n \n  <a href=\" https://imgmak.com/image/gVa\" rel=\"nofollow\" target=\"_NEW\"> https://imgmak.com/image/gVa</a>\n \n  <a href=\" https://imgmak.com/image/gVp\" rel=\"nofollow\" target=\"_NEW\"> https://imgmak.com/image/gVp</a>\n \n  <a href=\" https://imgmak.com/image/gVR\" rel=\"nofollow\" target=\"_NEW\"> https://imgmak.com/image/gVR</a>\n \n  <a href=\" https://imgmak.com/image/gVb\" rel=\"nofollow\" target=\"_NEW\"> https://imgmak.com/image/gVb</a>\n \n  <a href=\" https://imgmak.com/image/gVx\" rel=\"nofollow\" target=\"_NEW\"> https://imgmak.com/image/gVx</a>","last_updated":"2018-08-21T12:10:09.276Z","parsed":{"xt":"urn:btih:1f77b1b8fee2fcf384063e206bd1dca2fb05749a","dn":"Elementary.S06E17.1080p.WEB.x264-TBS[TGx]","tr":["udp://exodus.desync.com:6969","udp://open.demonii.com:1337","udp://tracker.coppersurfer.tk:6969","udp://tracker.leechers-paradise.org:6969","udp://zer0day.ch:1337"],"infoHash":"1f77b1b8fee2fcf384063e206bd1dca2fb05749a","infoHashBuffer":{"type":"Buffer","data":[31,119,177,184,254,226,252,243,132,6,62,32,107,209,220,162,251,5,116,154]},"name":"Elementary.S06E17.1080p.WEB.x264-TBS[TGx]","announce":["udp://exodus.desync.com:6969","udp://open.demonii.com:1337","udp://tracker.coppersurfer.tk:6969","udp://tracker.leechers-paradise.org:6969","udp://zer0day.ch:1337"],"urlList":[]}}