{"title":"Black.Ink.Crew.Chicago.S04E02.9Mag.Is.Dead.HDTV.x264-CRiMSON[...","magnet":"magnet:?xt=urn:btih:2048f95bc46084e58df214745bda83a8fb241ad3&dn=Black.Ink.Crew.Chicago.S04E02.9Mag.Is.Dead.HDTV.x264-CRiMSON%5B...&tr=udp%3A%2F%2Ftracker.leechers-paradise.org%3A6969&tr=udp%3A%2F%2Fzer0day.ch%3A1337&tr=udp%3A%2F%2Fopen.demonii.com%3A1337&tr=udp%3A%2F%2Ftracker.coppersurfer.tk%3A6969&tr=udp%3A%2F%2Fexodus.desync.com%3A6969","uploader":"ettv","categoryP":"video","categoryS":"tv_shows","size":"312019205","seeders":"23","leechers":"7","description":"\nEt TV Shows\r\n <a href=\"\nhttps://www.ettv.tv\" rel=\"nofollow\" target=\"_NEW\">\nhttps://www.ettv.tv</a>\n\nBlack.Ink.Crew.Chicago.S04E02.9Mag.Is.Dead.HDTV.x264-CRiMSON \r\n\n\n[Format]:    Matroska\n[Duration]:    40mn 41s\n[Resolution]:  720 x 404 pixels\n[Display aspect ratio]:    16:9\n[Frame rate mode]:    Constant\n[Frame rate]:    23.976 fps\n\r\n\n#ettv -&gt; To avoid fakes, ALWAYS check that the torrent was added by ettv\r\n\n\r\n\n\nTo keep us going Support us by donating Bitcoin: 1PDrQtCYeUFoRTsQaHTChAjrvAHbiVotPR\r\n\nScreens...\r <a href=\"\nhttps://extraimage.net/image/sjFt\" rel=\"nofollow\" target=\"_NEW\">\nhttps://extraimage.net/image/sjFt</a>","last_updated":"2018-06-07T12:07:11.986Z","parsed":{"xt":"urn:btih:2048f95bc46084e58df214745bda83a8fb241ad3","dn":"Black.Ink.Crew.Chicago.S04E02.9Mag.Is.Dead.HDTV.x264-CRiMSON[...","tr":["udp://exodus.desync.com:6969","udp://open.demonii.com:1337","udp://tracker.coppersurfer.tk:6969","udp://tracker.leechers-paradise.org:6969","udp://zer0day.ch:1337"],"infoHash":"2048f95bc46084e58df214745bda83a8fb241ad3","infoHashBuffer":{"type":"Buffer","data":[32,72,249,91,196,96,132,229,141,242,20,116,91,218,131,168,251,36,26,211]},"name":"Black.Ink.Crew.Chicago.S04E02.9Mag.Is.Dead.HDTV.x264-CRiMSON[...","announce":["udp://exodus.desync.com:6969","udp://open.demonii.com:1337","udp://tracker.coppersurfer.tk:6969","udp://tracker.leechers-paradise.org:6969","udp://zer0day.ch:1337"],"urlList":[]}}