{"title":"Jimmy.Kimmel.2018.05.16.Diane.Keaton.WEB.x264-TBS[N1C]","magnet":"magnet:?xt=urn:btih:25d79860fe1fcf0d4df10e2d67d1cad4ea073862&dn=Jimmy.Kimmel.2018.05.16.Diane.Keaton.WEB.x264-TBS%5BN1C%5D&tr=udp%3A%2F%2Ftracker.leechers-paradise.org%3A6969&tr=udp%3A%2F%2Fzer0day.ch%3A1337&tr=udp%3A%2F%2Fopen.demonii.com%3A1337&tr=udp%3A%2F%2Ftracker.coppersurfer.tk%3A6969&tr=udp%3A%2F%2Fexodus.desync.com%3A6969","uploader":"juggs99","categoryP":"video","categoryS":"tv_shows","size":"343024189","seeders":"5","leechers":"6","description":"Jimmy.Kimmel.2018.05.16.Diane.Keaton.WEB.x264-TBS[N1C]\n\n\n{Size} : 327 MiB\n{Duration} : 40 min 33 s\n{Resolution} : 992 x 558 pixels\n{Display aspect ratio} : 16:9\n{Frame Rate} : 29.940 fps\n{Video Bitrate} : 1 040 kb/s\n{Video Format Info} : Advanced Video Codec\n{Video Format} : AVC\n{Audio Format} : AAC\n{Audio Language} : \n{Audio Channels} : 2 CH\n\n\n#N1C -&gt; To avoid fakes, ALWAYS check that the torrent was added by NO1CARES \n\n\nHelp us by donating with Bitcoin: 1Pgwp16gmLHmPzgjJLxZnMw7YeqiUekUoe \n\n\nScreens...\n <a href=\"\nhttps://www.imgextra.uk/image/MF1\" rel=\"nofollow\" target=\"_NEW\">\nhttps://www.imgextra.uk/image/MF1</a> <a href=\"\nhttps://www.imgextra.uk/image/MFA\" rel=\"nofollow\" target=\"_NEW\">\nhttps://www.imgextra.uk/image/MFA</a> <a href=\"\nhttps://www.imgextra.uk/image/MFg\" rel=\"nofollow\" target=\"_NEW\">\nhttps://www.imgextra.uk/image/MFg</a> <a href=\"\nhttps://www.imgextra.uk/image/MFt\" rel=\"nofollow\" target=\"_NEW\">\nhttps://www.imgextra.uk/image/MFt</a>","last_updated":"2018-05-17T12:03:55.727Z","parsed":{"xt":"urn:btih:25d79860fe1fcf0d4df10e2d67d1cad4ea073862","dn":"Jimmy.Kimmel.2018.05.16.Diane.Keaton.WEB.x264-TBS[N1C]","tr":["udp://exodus.desync.com:6969","udp://open.demonii.com:1337","udp://tracker.coppersurfer.tk:6969","udp://tracker.leechers-paradise.org:6969","udp://zer0day.ch:1337"],"infoHash":"25d79860fe1fcf0d4df10e2d67d1cad4ea073862","infoHashBuffer":{"type":"Buffer","data":[37,215,152,96,254,31,207,13,77,241,14,45,103,209,202,212,234,7,56,98]},"name":"Jimmy.Kimmel.2018.05.16.Diane.Keaton.WEB.x264-TBS[N1C]","announce":["udp://exodus.desync.com:6969","udp://open.demonii.com:1337","udp://tracker.coppersurfer.tk:6969","udp://tracker.leechers-paradise.org:6969","udp://zer0day.ch:1337"],"urlList":[]}}