{"title":"DDFBusty - Angel Wicky - Satisfy Her XXX Needs","magnet":"magnet:?xt=urn:btih:263d297183e3eca385c4d1b3d7b12fc027153a31&dn=DDFBusty+-+Angel+Wicky+-+Satisfy+Her+XXX+Needs&tr=udp%3A%2F%2Ftracker.leechers-paradise.org%3A6969&tr=udp%3A%2F%2Fzer0day.ch%3A1337&tr=udp%3A%2F%2Fopen.demonii.com%3A1337&tr=udp%3A%2F%2Ftracker.coppersurfer.tk%3A6969&tr=udp%3A%2F%2Fexodus.desync.com%3A6969","uploader":"Borusssia","categoryP":"porn","categoryS":"movie_clips","size":"459427458","seeders":"14","leechers":"5","description":"Screens\r\n <a href=\"\nhttps://www.imgshots.com/img/15560/1.jpg\" rel=\"nofollow\" target=\"_NEW\">\nhttps://www.imgshots.com/img/15560/1.jpg</a>\r\n <a href=\"\nhttps://www.imgshots.com/img/15867/pic.jpg\" rel=\"nofollow\" target=\"_NEW\">\nhttps://www.imgshots.com/img/15867/pic.jpg</a>","last_updated":"2018-10-27T12:05:30.559Z","parsed":{"xt":"urn:btih:263d297183e3eca385c4d1b3d7b12fc027153a31","dn":"DDFBusty - Angel Wicky - Satisfy Her XXX Needs","tr":["udp://exodus.desync.com:6969","udp://open.demonii.com:1337","udp://tracker.coppersurfer.tk:6969","udp://tracker.leechers-paradise.org:6969","udp://zer0day.ch:1337"],"infoHash":"263d297183e3eca385c4d1b3d7b12fc027153a31","infoHashBuffer":{"type":"Buffer","data":[38,61,41,113,131,227,236,163,133,196,209,179,215,177,47,192,39,21,58,49]},"name":"DDFBusty - Angel Wicky - Satisfy Her XXX Needs","announce":["udp://exodus.desync.com:6969","udp://open.demonii.com:1337","udp://tracker.coppersurfer.tk:6969","udp://tracker.leechers-paradise.org:6969","udp://zer0day.ch:1337"],"urlList":[]}}