{"title":"HOT ANAL TEACHER","magnet":"magnet:?xt=urn:btih:30410d634791028888d47a78e1ece995a0c331b4&dn=HOT+ANAL+TEACHER&tr=udp%3A%2F%2Ftracker.leechers-paradise.org%3A6969&tr=udp%3A%2F%2Fzer0day.ch%3A1337&tr=udp%3A%2F%2Fopen.demonii.com%3A1337&tr=udp%3A%2F%2Ftracker.coppersurfer.tk%3A6969&tr=udp%3A%2F%2Fexodus.desync.com%3A6969","uploader":"qwe5678","categoryP":"porn","categoryS":"hd___movies","size":"2254695119","seeders":"1","leechers":"12","description":" <a href=\"http://picfuture.com/img-5b4f0c95aff84.html\" rel=\"nofollow\" target=\"_NEW\">http://picfuture.com/img-5b4f0c95aff84.html</a> <a href=\"\nhttp://picfuture.com/img-5b4f0c95b3489.html\" rel=\"nofollow\" target=\"_NEW\">\nhttp://picfuture.com/img-5b4f0c95b3489.html</a>","last_updated":"2018-07-18T12:12:06.632Z","parsed":{"xt":"urn:btih:30410d634791028888d47a78e1ece995a0c331b4","dn":"HOT ANAL TEACHER","tr":["udp://exodus.desync.com:6969","udp://open.demonii.com:1337","udp://tracker.coppersurfer.tk:6969","udp://tracker.leechers-paradise.org:6969","udp://zer0day.ch:1337"],"infoHash":"30410d634791028888d47a78e1ece995a0c331b4","infoHashBuffer":{"type":"Buffer","data":[48,65,13,99,71,145,2,136,136,212,122,120,225,236,233,149,160,195,49,180]},"name":"HOT ANAL TEACHER","announce":["udp://exodus.desync.com:6969","udp://open.demonii.com:1337","udp://tracker.coppersurfer.tk:6969","udp://tracker.leechers-paradise.org:6969","udp://zer0day.ch:1337"],"urlList":[]}}