{"title":"Flog.It.Trade.Secrets.S01E09.XviD-AFG[TGx]","magnet":"magnet:?xt=urn:btih:37c21c8ded78afe1eed871d102041da648cd495a&dn=Flog.It.Trade.Secrets.S01E09.XviD-AFG%5BTGx%5D&tr=udp%3A%2F%2Ftracker.leechers-paradise.org%3A6969&tr=udp%3A%2F%2Fzer0day.ch%3A1337&tr=udp%3A%2F%2Fopen.demonii.com%3A1337&tr=udp%3A%2F%2Ftracker.coppersurfer.tk%3A6969&tr=udp%3A%2F%2Fexodus.desync.com%3A6969","uploader":"makintos13","categoryP":"video","categoryS":"tv_shows","size":"366924380","seeders":"2","leechers":"4","description":"Flog.It.Trade.Secrets.S01E09.XviD-AFG[TGx]\n \n MEDIAINFO\n Container = AVI (avi)\n Duration = 00:29:12.000\n Filesize = 348 MiB\n --Video\n Codec info = xvid | xvid\n Resolution = 640x360\n Display AR = 1.778 | 16:9\n Bitrate = 1 527 kb/s\n Framerate = 25.000\n Color space = \n Chroma subsampling = \n Encoder = \n --Audio\n Codec info = MPEG Audio Layer 3 | 55\n Channels = 2\n Bitrate = CBR 128 kb/s\n Samplerate = 48.0 kHz\n Language = English\n \n SCREENSHOTS  <a href=\" https://imgmak.com/image/3WI\" rel=\"nofollow\" target=\"_NEW\"> https://imgmak.com/image/3WI</a>  <a href=\" https://imgmak.com/image/3Wq\" rel=\"nofollow\" target=\"_NEW\"> https://imgmak.com/image/3Wq</a>  <a href=\" https://imgmak.com/image/3Wt\" rel=\"nofollow\" target=\"_NEW\"> https://imgmak.com/image/3Wt</a>  <a href=\" https://imgmak.com/image/3W2\" rel=\"nofollow\" target=\"_NEW\"> https://imgmak.com/image/3W2</a>  <a href=\" https://imgmak.com/image/3WF\" rel=\"nofollow\" target=\"_NEW\"> https://imgmak.com/image/3WF</a>  <a href=\" https://imgmak.com/image/3Wi\" rel=\"nofollow\" target=\"_NEW\"> https://imgmak.com/image/3Wi</a>","last_updated":"2018-04-28T12:05:21.742Z","parsed":{"xt":"urn:btih:37c21c8ded78afe1eed871d102041da648cd495a","dn":"Flog.It.Trade.Secrets.S01E09.XviD-AFG[TGx]","tr":["udp://exodus.desync.com:6969","udp://open.demonii.com:1337","udp://tracker.coppersurfer.tk:6969","udp://tracker.leechers-paradise.org:6969","udp://zer0day.ch:1337"],"infoHash":"37c21c8ded78afe1eed871d102041da648cd495a","infoHashBuffer":{"type":"Buffer","data":[55,194,28,141,237,120,175,225,238,216,113,209,2,4,29,166,72,205,73,90]},"name":"Flog.It.Trade.Secrets.S01E09.XviD-AFG[TGx]","announce":["udp://exodus.desync.com:6969","udp://open.demonii.com:1337","udp://tracker.coppersurfer.tk:6969","udp://tracker.leechers-paradise.org:6969","udp://zer0day.ch:1337"],"urlList":[]}}