{"title":"The.Cool.Kids.S01E03.HDTV.x264-SVA[ettv]","magnet":"magnet:?xt=urn:btih:38637bf168f947303afaf54e424eb74c5afaec47&dn=The.Cool.Kids.S01E03.HDTV.x264-SVA%5Bettv%5D&tr=udp%3A%2F%2Ftracker.leechers-paradise.org%3A6969&tr=udp%3A%2F%2Fzer0day.ch%3A1337&tr=udp%3A%2F%2Fopen.demonii.com%3A1337&tr=udp%3A%2F%2Ftracker.coppersurfer.tk%3A6969&tr=udp%3A%2F%2Fexodus.desync.com%3A6969","uploader":"ettv","categoryP":"video","categoryS":"tv_shows","size":"167030283","seeders":"53","leechers":"18","description":"Et TV Shows\r\n\r\n <a href=\"\nhttps://www.ettv.be/home/\" rel=\"nofollow\" target=\"_NEW\">\nhttps://www.ettv.be/home/</a>\r\n\r\nThe.Cool.Kids.S01E03.HDTV.x264-SVA\r\n\r\n\r\n[Format]:    Matroska\r\n[Duration]:    21mn 16s\r\n[Resolution]:  720 x 404 pixels\r\n[Display aspect ratio]:    16:9\r\n[Frame rate mode]:    Constant\r\n[Frame rate]:    23.976 fps\r\n\r\n\r\n#ettv -&gt; To avoid fakes, ALWAYS check that the torrent was added by ettv\r\n\r\n\r\n\r\n\r\nTo keep us going Support us by donating Bitcoin: 3PaWcF82GoygLH9z4d7AocH6zcF6m15Wdv\r\n\r\nScreens...\r\n <a href=\"\nhttps://extraimage.net/image/79Xy\" rel=\"nofollow\" target=\"_NEW\">\nhttps://extraimage.net/image/79Xy</a>","last_updated":"2018-10-11T12:19:04.667Z","parsed":{"xt":"urn:btih:38637bf168f947303afaf54e424eb74c5afaec47","dn":"The.Cool.Kids.S01E03.HDTV.x264-SVA[ettv]","tr":["udp://exodus.desync.com:6969","udp://open.demonii.com:1337","udp://tracker.coppersurfer.tk:6969","udp://tracker.leechers-paradise.org:6969","udp://zer0day.ch:1337"],"infoHash":"38637bf168f947303afaf54e424eb74c5afaec47","infoHashBuffer":{"type":"Buffer","data":[56,99,123,241,104,249,71,48,58,250,245,78,66,78,183,76,90,250,236,71]},"name":"The.Cool.Kids.S01E03.HDTV.x264-SVA[ettv]","announce":["udp://exodus.desync.com:6969","udp://open.demonii.com:1337","udp://tracker.coppersurfer.tk:6969","udp://tracker.leechers-paradise.org:6969","udp://zer0day.ch:1337"],"urlList":[]}}