{"title":"PegasProductions.18.01.23.Sandy.Sugarlips.Hot.Chix.On.The.Leash","magnet":"magnet:?xt=urn:btih:54f5e643e9cd2026af4aac2be2656869001721eb&dn=PegasProductions.18.01.23.Sandy.Sugarlips.Hot.Chix.On.The.Leash&tr=udp%3A%2F%2Ftracker.leechers-paradise.org%3A6969&tr=udp%3A%2F%2Fzer0day.ch%3A1337&tr=udp%3A%2F%2Fopen.demonii.com%3A1337&tr=udp%3A%2F%2Ftracker.coppersurfer.tk%3A6969&tr=udp%3A%2F%2Fexodus.desync.com%3A6969","uploader":"WankPorn","categoryP":"porn","categoryS":"hd___movies","size":"1610023633","seeders":"0","leechers":"0","description":"PegasProductions.18.01.23.Sandy.Sugarlips.Hot.Chix.On.The.Leash.FRENCH.XXX.1080p.MP4-KTR\n\n\n{Duration} : 27 min 59 s\n{Format} : MPEG-4\n{Resolution} : 1920 x 1080 pixels\n{Aspect Ratio} : 16:9\n{Frame Rate} : 29.970 fps\n\n\nThumbnails : -\n\n <a href=\"\nhttps://hot.sizzlingclicks.com/image/3QdkK\" rel=\"nofollow\" target=\"_NEW\">\nhttps://hot.sizzlingclicks.com/image/3QdkK</a>\n <a href=\"\nhttps://hot.sizzlingclicks.com/image/3Qn83\" rel=\"nofollow\" target=\"_NEW\">\nhttps://hot.sizzlingclicks.com/image/3Qn83</a>\n <a href=\"\nhttps://hot.sizzlingclicks.com/image/3Qqxe\" rel=\"nofollow\" target=\"_NEW\">\nhttps://hot.sizzlingclicks.com/image/3Qqxe</a>\n <a href=\"\nhttps://hot.sizzlingclicks.com/image/3QyAi\" rel=\"nofollow\" target=\"_NEW\">\nhttps://hot.sizzlingclicks.com/image/3QyAi</a>","last_updated":"2018-01-30T12:08:00.832Z","parsed":{"xt":"urn:btih:54f5e643e9cd2026af4aac2be2656869001721eb","dn":"PegasProductions.18.01.23.Sandy.Sugarlips.Hot.Chix.On.The.Leash","tr":["udp://exodus.desync.com:6969","udp://open.demonii.com:1337","udp://tracker.coppersurfer.tk:6969","udp://tracker.leechers-paradise.org:6969","udp://zer0day.ch:1337"],"infoHash":"54f5e643e9cd2026af4aac2be2656869001721eb","infoHashBuffer":{"type":"Buffer","data":[84,245,230,67,233,205,32,38,175,74,172,43,226,101,104,105,0,23,33,235]},"name":"PegasProductions.18.01.23.Sandy.Sugarlips.Hot.Chix.On.The.Leash","announce":["udp://exodus.desync.com:6969","udp://open.demonii.com:1337","udp://tracker.coppersurfer.tk:6969","udp://tracker.leechers-paradise.org:6969","udp://zer0day.ch:1337"],"urlList":[]}}