{"title":"[WoodmanCastingX] Carly Rae (Casting X 160 Updated - 15.07.2018)","magnet":"magnet:?xt=urn:btih:576af0eae1136ece74f7a730caca2b3bd875fded&dn=%5BWoodmanCastingX%5D+Carly+Rae+%28Casting+X+160+Updated+-+15.07.2018%29&tr=udp%3A%2F%2Ftracker.leechers-paradise.org%3A6969&tr=udp%3A%2F%2Fzer0day.ch%3A1337&tr=udp%3A%2F%2Fopen.demonii.com%3A1337&tr=udp%3A%2F%2Ftracker.coppersurfer.tk%3A6969&tr=udp%3A%2F%2Fexodus.desync.com%3A6969","uploader":"KayWily","categoryP":"porn","categoryS":"movie_clips","size":"1247687807","seeders":"54","leechers":"46","description":"[WoodmanCastingX] Carly Rae (Casting X 160 Updated - 15.07.2018)\r\n\r\n <a href=\"\nhttp://ipicture.su//img-5b4d8ec8df3ad.html\" rel=\"nofollow\" target=\"_NEW\">\nhttp://ipicture.su//img-5b4d8ec8df3ad.html</a>","last_updated":"2018-07-17T12:09:25.775Z","parsed":{"xt":"urn:btih:576af0eae1136ece74f7a730caca2b3bd875fded","dn":"[WoodmanCastingX] Carly Rae (Casting X 160 Updated - 15.07.2018)","tr":["udp://exodus.desync.com:6969","udp://open.demonii.com:1337","udp://tracker.coppersurfer.tk:6969","udp://tracker.leechers-paradise.org:6969","udp://zer0day.ch:1337"],"infoHash":"576af0eae1136ece74f7a730caca2b3bd875fded","infoHashBuffer":{"type":"Buffer","data":[87,106,240,234,225,19,110,206,116,247,167,48,202,202,43,59,216,117,253,237]},"name":"[WoodmanCastingX] Carly Rae (Casting X 160 Updated - 15.07.2018)","announce":["udp://exodus.desync.com:6969","udp://open.demonii.com:1337","udp://tracker.coppersurfer.tk:6969","udp://tracker.leechers-paradise.org:6969","udp://zer0day.ch:1337"],"urlList":[]}}