{"title":"Foxit PhantomPDF Business 9.0.0.29935 + Crack","magnet":"magnet:?xt=urn:btih:593f4b096e9d4061768d78a3e4da14537410970b&dn=Foxit+PhantomPDF+Business+9.0.0.29935+%2B+Crack&tr=udp%3A%2F%2Ftracker.leechers-paradise.org%3A6969&tr=udp%3A%2F%2Fzer0day.ch%3A1337&tr=udp%3A%2F%2Fopen.demonii.com%3A1337&tr=udp%3A%2F%2Ftracker.coppersurfer.tk%3A6969&tr=udp%3A%2F%2Fexodus.desync.com%3A6969","uploader":"megnebiltew","categoryP":"applications","categoryS":"windows","size":"7666114","seeders":"558","leechers":"373","description":"1) Unpack and install\r\n2) Use the key generator to generate a valid serial\r\n3) Enjoy this release!\r\n\r\nDon&apos;t Forget to buy the program","last_updated":"2018-01-29T12:11:06.505Z","parsed":{"xt":"urn:btih:593f4b096e9d4061768d78a3e4da14537410970b","dn":"Foxit PhantomPDF Business 9.0.0.29935   Crack","tr":["udp://exodus.desync.com:6969","udp://open.demonii.com:1337","udp://tracker.coppersurfer.tk:6969","udp://tracker.leechers-paradise.org:6969","udp://zer0day.ch:1337"],"infoHash":"593f4b096e9d4061768d78a3e4da14537410970b","infoHashBuffer":{"type":"Buffer","data":[89,63,75,9,110,157,64,97,118,141,120,163,228,218,20,83,116,16,151,11]},"name":"Foxit PhantomPDF Business 9.0.0.29935   Crack","announce":["udp://exodus.desync.com:6969","udp://open.demonii.com:1337","udp://tracker.coppersurfer.tk:6969","udp://tracker.leechers-paradise.org:6969","udp://zer0day.ch:1337"],"urlList":[]}}