{"title":"Victoria Pure - Keep your heels on","magnet":"magnet:?xt=urn:btih:6c1202a35faf6a291726ca76670e7e52218ec4e1&dn=Victoria+Pure+-+Keep+your+heels+on&tr=udp%3A%2F%2Ftracker.leechers-paradise.org%3A6969&tr=udp%3A%2F%2Fzer0day.ch%3A1337&tr=udp%3A%2F%2Fopen.demonii.com%3A1337&tr=udp%3A%2F%2Ftracker.coppersurfer.tk%3A6969&tr=udp%3A%2F%2Fexodus.desync.com%3A6969","uploader":"adderiyk","categoryP":"porn","categoryS":"hd___movies","size":"479533742","seeders":"7","leechers":"10","description":" <a href=\"http://imgsalem.com/img-5b499fca8fa1a.html\" rel=\"nofollow\" target=\"_NEW\">http://imgsalem.com/img-5b499fca8fa1a.html</a> <a href=\"\nhttp://imgsalem.com/img-5b499fcaaa386.html\" rel=\"nofollow\" target=\"_NEW\">\nhttp://imgsalem.com/img-5b499fcaaa386.html</a>","last_updated":"2018-07-14T12:08:49.534Z","parsed":{"xt":"urn:btih:6c1202a35faf6a291726ca76670e7e52218ec4e1","dn":"Victoria Pure - Keep your heels on","tr":["udp://exodus.desync.com:6969","udp://open.demonii.com:1337","udp://tracker.coppersurfer.tk:6969","udp://tracker.leechers-paradise.org:6969","udp://zer0day.ch:1337"],"infoHash":"6c1202a35faf6a291726ca76670e7e52218ec4e1","infoHashBuffer":{"type":"Buffer","data":[108,18,2,163,95,175,106,41,23,38,202,118,103,14,126,82,33,142,196,225]},"name":"Victoria Pure - Keep your heels on","announce":["udp://exodus.desync.com:6969","udp://open.demonii.com:1337","udp://tracker.coppersurfer.tk:6969","udp://tracker.leechers-paradise.org:6969","udp://zer0day.ch:1337"],"urlList":[]}}