{"title":"FC2-PPV-883230","magnet":"magnet:?xt=urn:btih:6e9a02863e6faa24db4786543b19b9bb23cee89f&dn=FC2-PPV-883230&tr=udp%3A%2F%2Ftracker.leechers-paradise.org%3A6969&tr=udp%3A%2F%2Fzer0day.ch%3A1337&tr=udp%3A%2F%2Fopen.demonii.com%3A1337&tr=udp%3A%2F%2Ftracker.coppersurfer.tk%3A6969&tr=udp%3A%2F%2Fexodus.desync.com%3A6969","uploader":"javminer","categoryP":"porn","categoryS":"movies","size":"1771367136","seeders":"139","leechers":"193","description":"FC2-PPV-883230\r\n\r\n\r\nSCreen SHots-&gt;\r\n\r\n <a href=\"\nhttp://javfreestreaming.com/fc2-ppv-883230\" rel=\"nofollow\" target=\"_NEW\">\nhttp://javfreestreaming.com/fc2-ppv-883230</a>","last_updated":"2018-07-19T12:04:55.478Z","parsed":{"xt":"urn:btih:6e9a02863e6faa24db4786543b19b9bb23cee89f","dn":"FC2-PPV-883230","tr":["udp://exodus.desync.com:6969","udp://open.demonii.com:1337","udp://tracker.coppersurfer.tk:6969","udp://tracker.leechers-paradise.org:6969","udp://zer0day.ch:1337"],"infoHash":"6e9a02863e6faa24db4786543b19b9bb23cee89f","infoHashBuffer":{"type":"Buffer","data":[110,154,2,134,62,111,170,36,219,71,134,84,59,25,185,187,35,206,232,159]},"name":"FC2-PPV-883230","announce":["udp://exodus.desync.com:6969","udp://open.demonii.com:1337","udp://tracker.coppersurfer.tk:6969","udp://tracker.leechers-paradise.org:6969","udp://zer0day.ch:1337"],"urlList":[]}}