{"title":"Naked.and.Afraid.XL.S04E01.All-Stars.Hunted.Humans.720p.HDTV.x2","magnet":"magnet:?xt=urn:btih:72b6ca56c5651ad4cf57d55924ea0b99c8ab1848&dn=Naked.and.Afraid.XL.S04E01.All-Stars.Hunted.Humans.720p.HDTV.x2&tr=udp%3A%2F%2Ftracker.leechers-paradise.org%3A6969&tr=udp%3A%2F%2Fzer0day.ch%3A1337&tr=udp%3A%2F%2Fopen.demonii.com%3A1337&tr=udp%3A%2F%2Ftracker.coppersurfer.tk%3A6969&tr=udp%3A%2F%2Fexodus.desync.com%3A6969","uploader":"juggs99","categoryP":"video","categoryS":"hd___tv_shows","size":"1902810844","seeders":"3","leechers":"10","description":"Naked.and.Afraid.XL.S04E01.All-Stars.Hunted.Humans.720p.HDTV.x264-CRiMSON[N1C]\n\n\n{Size} : 1.77 GiB\n{Duration} : 41 min 31 s\n{Resolution} : 1280 x 720 pixels\n{Display aspect ratio} : 16:9\n{Frame Rate} : 29.970 fps\n{Video Bitrate} : 5 723 kb/s\n{Video Format Info} : Advanced Video Codec\n{Video Format} : AVC\n{Audio Format} : AC-3\n{Audio Language} : \n{Audio Channels} : 6 CH\n\n\n#N1C -&gt; To avoid fakes, ALWAYS check that the torrent was added by NO1CARES \n\n\nHelp us by donating with Bitcoin: 1Pgwp16gmLHmPzgjJLxZnMw7YeqiUekUoe \n\n\nScreens...\n <a href=\"\nhttps://www.imgextra.uk/image/UUk\" rel=\"nofollow\" target=\"_NEW\">\nhttps://www.imgextra.uk/image/UUk</a> <a href=\"\nhttps://www.imgextra.uk/image/UUu\" rel=\"nofollow\" target=\"_NEW\">\nhttps://www.imgextra.uk/image/UUu</a> <a href=\"\nhttps://www.imgextra.uk/image/UU5\" rel=\"nofollow\" target=\"_NEW\">\nhttps://www.imgextra.uk/image/UU5</a> <a href=\"\nhttps://www.imgextra.uk/image/UUR\" rel=\"nofollow\" target=\"_NEW\">\nhttps://www.imgextra.uk/image/UUR</a>","last_updated":"2018-05-07T12:10:51.738Z","parsed":{"xt":"urn:btih:72b6ca56c5651ad4cf57d55924ea0b99c8ab1848","dn":"Naked.and.Afraid.XL.S04E01.All-Stars.Hunted.Humans.720p.HDTV.x2","tr":["udp://exodus.desync.com:6969","udp://open.demonii.com:1337","udp://tracker.coppersurfer.tk:6969","udp://tracker.leechers-paradise.org:6969","udp://zer0day.ch:1337"],"infoHash":"72b6ca56c5651ad4cf57d55924ea0b99c8ab1848","infoHashBuffer":{"type":"Buffer","data":[114,182,202,86,197,101,26,212,207,87,213,89,36,234,11,153,200,171,24,72]},"name":"Naked.and.Afraid.XL.S04E01.All-Stars.Hunted.Humans.720p.HDTV.x2","announce":["udp://exodus.desync.com:6969","udp://open.demonii.com:1337","udp://tracker.coppersurfer.tk:6969","udp://tracker.leechers-paradise.org:6969","udp://zer0day.ch:1337"],"urlList":[]}}