{"title":"Icecream Screen Recorder Pro 5.21 + Crack","magnet":"magnet:?xt=urn:btih:7433595768ed96b7acb0143d1e3e019b91d6446a&dn=Icecream+Screen+Recorder+Pro+5.21+%2B+Crack&tr=udp%3A%2F%2Ftracker.leechers-paradise.org%3A6969&tr=udp%3A%2F%2Fzer0day.ch%3A1337&tr=udp%3A%2F%2Fopen.demonii.com%3A1337&tr=udp%3A%2F%2Ftracker.coppersurfer.tk%3A6969&tr=udp%3A%2F%2Fexodus.desync.com%3A6969","uploader":"ghjkowmebfl","categoryP":"applications","categoryS":"windows","size":"6358101","seeders":"0","leechers":"0","description":"\r\n=&gt; UPDATED Files. &lt;=\r\n\r\n[ ABOUT ]\r\n\r\n       *&gt; This Software has been UPDATED on 2018.\r\n       *&gt; To get more new Feature, You can Download and install.\r\n       *&gt; More new Feature ADDED to it.\r\n\r\n\r\n*&gt; Install and Enjoy","last_updated":"2018-05-02T12:04:27.178Z","parsed":{"xt":"urn:btih:7433595768ed96b7acb0143d1e3e019b91d6446a","dn":"Icecream Screen Recorder Pro 5.21   Crack","tr":["udp://exodus.desync.com:6969","udp://open.demonii.com:1337","udp://tracker.coppersurfer.tk:6969","udp://tracker.leechers-paradise.org:6969","udp://zer0day.ch:1337"],"infoHash":"7433595768ed96b7acb0143d1e3e019b91d6446a","infoHashBuffer":{"type":"Buffer","data":[116,51,89,87,104,237,150,183,172,176,20,61,30,62,1,155,145,214,68,106]},"name":"Icecream Screen Recorder Pro 5.21   Crack","announce":["udp://exodus.desync.com:6969","udp://open.demonii.com:1337","udp://tracker.coppersurfer.tk:6969","udp://tracker.leechers-paradise.org:6969","udp://zer0day.ch:1337"],"urlList":[]}}