{"title":"[AnalTeenAngels/ 21Sextury] Zazie Skymm - Curious Teen ","magnet":"magnet:?xt=urn:btih:7ef63c3d61f4b7d64aa7e28e1b57517fe706845d&dn=%5BAnalTeenAngels%2F+21Sextury%5D+Zazie+Skymm+-+Curious+Teen+&tr=udp%3A%2F%2Ftracker.leechers-paradise.org%3A6969&tr=udp%3A%2F%2Fzer0day.ch%3A1337&tr=udp%3A%2F%2Fopen.demonii.com%3A1337&tr=udp%3A%2F%2Ftracker.coppersurfer.tk%3A6969&tr=udp%3A%2F%2Fexodus.desync.com%3A6969","uploader":"qwe5678","categoryP":"porn","categoryS":"hd___movies","size":"1574650088","seeders":"28","leechers":"10","description":" <a href=\"http://picfuture.com/img-5b7b92c373de2.html\" rel=\"nofollow\" target=\"_NEW\">http://picfuture.com/img-5b7b92c373de2.html</a> <a href=\"\nhttp://picfuture.com/img-5b7b92c378515.html\" rel=\"nofollow\" target=\"_NEW\">\nhttp://picfuture.com/img-5b7b92c378515.html</a>","last_updated":"2018-08-21T12:12:41.506Z","parsed":{"xt":"urn:btih:7ef63c3d61f4b7d64aa7e28e1b57517fe706845d","dn":"[AnalTeenAngels/ 21Sextury] Zazie Skymm - Curious Teen ","tr":["udp://exodus.desync.com:6969","udp://open.demonii.com:1337","udp://tracker.coppersurfer.tk:6969","udp://tracker.leechers-paradise.org:6969","udp://zer0day.ch:1337"],"infoHash":"7ef63c3d61f4b7d64aa7e28e1b57517fe706845d","infoHashBuffer":{"type":"Buffer","data":[126,246,60,61,97,244,183,214,74,167,226,142,27,87,81,127,231,6,132,93]},"name":"[AnalTeenAngels/ 21Sextury] Zazie Skymm - Curious Teen ","announce":["udp://exodus.desync.com:6969","udp://open.demonii.com:1337","udp://tracker.coppersurfer.tk:6969","udp://tracker.leechers-paradise.org:6969","udp://zer0day.ch:1337"],"urlList":[]}}