{"title":"[BrazzersExxtra] Alexis Fawx (Plump As A Peach / 21.03.2018)","magnet":"magnet:?xt=urn:btih:84ccfb27b200d8a60ad9f6975dced991912ee4fd&dn=%5BBrazzersExxtra%5D+Alexis+Fawx+%28Plump+As+A+Peach+%2F+21.03.2018%29&tr=udp%3A%2F%2Ftracker.leechers-paradise.org%3A6969&tr=udp%3A%2F%2Fzer0day.ch%3A1337&tr=udp%3A%2F%2Fopen.demonii.com%3A1337&tr=udp%3A%2F%2Ftracker.coppersurfer.tk%3A6969&tr=udp%3A%2F%2Fexodus.desync.com%3A6969","uploader":"Vikcy41","categoryP":"porn","categoryS":"hd___movies","size":"1529686842","seeders":"0","leechers":"0","description":"[BrazzersExxtra] Alexis Fawx (Plump As A Peach / 21.03.2018)\r\n <a href=\"\nhttp://xyzimage.net/img-5ab1d25a6252f.html\" rel=\"nofollow\" target=\"_NEW\">\nhttp://xyzimage.net/img-5ab1d25a6252f.html</a>\r\n <a href=\"\nhttp://xyzimage.net/img-5ab1da4591227.html\" rel=\"nofollow\" target=\"_NEW\">\nhttp://xyzimage.net/img-5ab1da4591227.html</a>\r\n <a href=\"\nhttp://xyzimage.net/img-5ab1d25e16fa2.html\" rel=\"nofollow\" target=\"_NEW\">\nhttp://xyzimage.net/img-5ab1d25e16fa2.html</a>\r\n <a href=\"\nhttp://xyzimage.net/img-5ab1d242eaf55.html\" rel=\"nofollow\" target=\"_NEW\">\nhttp://xyzimage.net/img-5ab1d242eaf55.html</a>","last_updated":"2018-03-21T13:02:24.061Z","parsed":{"xt":"urn:btih:84ccfb27b200d8a60ad9f6975dced991912ee4fd","dn":"[BrazzersExxtra] Alexis Fawx (Plump As A Peach / 21.03.2018)","tr":["udp://exodus.desync.com:6969","udp://open.demonii.com:1337","udp://tracker.coppersurfer.tk:6969","udp://tracker.leechers-paradise.org:6969","udp://zer0day.ch:1337"],"infoHash":"84ccfb27b200d8a60ad9f6975dced991912ee4fd","infoHashBuffer":{"type":"Buffer","data":[132,204,251,39,178,0,216,166,10,217,246,151,93,206,217,145,145,46,228,253]},"name":"[BrazzersExxtra] Alexis Fawx (Plump As A Peach / 21.03.2018)","announce":["udp://exodus.desync.com:6969","udp://open.demonii.com:1337","udp://tracker.coppersurfer.tk:6969","udp://tracker.leechers-paradise.org:6969","udp://zer0day.ch:1337"],"urlList":[]}}