{"title":"Looney.Tunes-Porkys.Duck.Hunt.1937.DVDRip.x264-REGRET","magnet":"magnet:?xt=urn:btih:8e12b5b6daf8f1e3deade07d7a8629acb7a8ede5&dn=Looney.Tunes-Porkys.Duck.Hunt.1937.DVDRip.x264-REGRET&tr=udp%3A%2F%2Ftracker.leechers-paradise.org%3A6969&tr=udp%3A%2F%2Fzer0day.ch%3A1337&tr=udp%3A%2F%2Fopen.demonii.com%3A1337&tr=udp%3A%2F%2Ftracker.coppersurfer.tk%3A6969&tr=udp%3A%2F%2Fexodus.desync.com%3A6969","uploader":"TvTeam","categoryP":"video","categoryS":"tv_shows","size":"106840086","seeders":"0","leechers":"0","description":"Torrent is coming from:\r\n~~~~~~~~~~~~~~~~~~~~~~~~~~~~~\r\n <a href=\"\nhttps://torrenting.me\" rel=\"nofollow\" target=\"_NEW\">\nhttps://torrenting.me</a>\r\n\r\n~~~~~~~~~~~~~~~~~~~~~~~~~~~~~\r\n\r\nJoin us and become part of the BIG family! Yarrrrrrrrrrrrrr!!!","last_updated":"2018-05-08T12:00:35.377Z","parsed":{"xt":"urn:btih:8e12b5b6daf8f1e3deade07d7a8629acb7a8ede5","dn":"Looney.Tunes-Porkys.Duck.Hunt.1937.DVDRip.x264-REGRET","tr":["udp://exodus.desync.com:6969","udp://open.demonii.com:1337","udp://tracker.coppersurfer.tk:6969","udp://tracker.leechers-paradise.org:6969","udp://zer0day.ch:1337"],"infoHash":"8e12b5b6daf8f1e3deade07d7a8629acb7a8ede5","infoHashBuffer":{"type":"Buffer","data":[142,18,181,182,218,248,241,227,222,173,224,125,122,134,41,172,183,168,237,229]},"name":"Looney.Tunes-Porkys.Duck.Hunt.1937.DVDRip.x264-REGRET","announce":["udp://exodus.desync.com:6969","udp://open.demonii.com:1337","udp://tracker.coppersurfer.tk:6969","udp://tracker.leechers-paradise.org:6969","udp://zer0day.ch:1337"],"urlList":[]}}