{"title":"UnREAL.S04E07.XviD-AFG","magnet":"magnet:?xt=urn:btih:8fa6cef460e8286a98301fe0fd327f111f73a3fd&dn=UnREAL.S04E07.XviD-AFG&tr=udp%3A%2F%2Ftracker.leechers-paradise.org%3A6969&tr=udp%3A%2F%2Fzer0day.ch%3A1337&tr=udp%3A%2F%2Fopen.demonii.com%3A1337&tr=udp%3A%2F%2Ftracker.coppersurfer.tk%3A6969&tr=udp%3A%2F%2Fexodus.desync.com%3A6969","uploader":"TvTeam","categoryP":"video","categoryS":"tv_shows","size":"420484704","seeders":"9","leechers":"10","description":"Torrent is coming from:\r\n~~~~~~~~~~~~~~~~~~~~~~~~~~~~~\r\n <a href=\"\nhttps://torrenting.me\" rel=\"nofollow\" target=\"_NEW\">\nhttps://torrenting.me</a>\r\n\r\n~~~~~~~~~~~~~~~~~~~~~~~~~~~~~\r\n\r\nJoin us and become part of the BIG family! Yarrrrrrrrrrrrrr!!!","last_updated":"2018-07-17T12:15:03.820Z","parsed":{"xt":"urn:btih:8fa6cef460e8286a98301fe0fd327f111f73a3fd","dn":"UnREAL.S04E07.XviD-AFG","tr":["udp://exodus.desync.com:6969","udp://open.demonii.com:1337","udp://tracker.coppersurfer.tk:6969","udp://tracker.leechers-paradise.org:6969","udp://zer0day.ch:1337"],"infoHash":"8fa6cef460e8286a98301fe0fd327f111f73a3fd","infoHashBuffer":{"type":"Buffer","data":[143,166,206,244,96,232,40,106,152,48,31,224,253,50,127,17,31,115,163,253]},"name":"UnREAL.S04E07.XviD-AFG","announce":["udp://exodus.desync.com:6969","udp://open.demonii.com:1337","udp://tracker.coppersurfer.tk:6969","udp://tracker.leechers-paradise.org:6969","udp://zer0day.ch:1337"],"urlList":[]}}