{"title":"NuruMassage - FantasyMassage - Sloan Harper - A Busty Upgrade (1","magnet":"magnet:?xt=urn:btih:990312c0390c14429347b0409a6f76a609becfa3&dn=NuruMassage+-+FantasyMassage+-+Sloan+Harper+-+A+Busty+Upgrade+%281&tr=udp%3A%2F%2Ftracker.leechers-paradise.org%3A6969&tr=udp%3A%2F%2Fzer0day.ch%3A1337&tr=udp%3A%2F%2Fopen.demonii.com%3A1337&tr=udp%3A%2F%2Ftracker.coppersurfer.tk%3A6969&tr=udp%3A%2F%2Fexodus.desync.com%3A6969","uploader":"MST","categoryP":"porn","categoryS":"hd___movies","size":"1675340524","seeders":"1","leechers":"2","description":"NuruMassage - FantasyMassage - Sloan Harper - A Busty Upgrade (17.08.2018) 1080\r\n\r\nScreens\r\n <a href=\"\nhttps://mstimg.com/image/CSxE\" rel=\"nofollow\" target=\"_NEW\">\nhttps://mstimg.com/image/CSxE</a> <a href=\"\nhttps://mstimg.com/image/CPvn\" rel=\"nofollow\" target=\"_NEW\">\nhttps://mstimg.com/image/CPvn</a> <a href=\"\nhttps://mstimg.com/image/Cpy0\" rel=\"nofollow\" target=\"_NEW\">\nhttps://mstimg.com/image/Cpy0</a> <a href=\"\nhttps://mstimg.com/image/Ct29\" rel=\"nofollow\" target=\"_NEW\">\nhttps://mstimg.com/image/Ct29</a>","last_updated":"2018-08-17T12:09:53.660Z","parsed":{"xt":"urn:btih:990312c0390c14429347b0409a6f76a609becfa3","dn":"NuruMassage - FantasyMassage - Sloan Harper - A Busty Upgrade (1","tr":["udp://exodus.desync.com:6969","udp://open.demonii.com:1337","udp://tracker.coppersurfer.tk:6969","udp://tracker.leechers-paradise.org:6969","udp://zer0day.ch:1337"],"infoHash":"990312c0390c14429347b0409a6f76a609becfa3","infoHashBuffer":{"type":"Buffer","data":[153,3,18,192,57,12,20,66,147,71,176,64,154,111,118,166,9,190,207,163]},"name":"NuruMassage - FantasyMassage - Sloan Harper - A Busty Upgrade (1","announce":["udp://exodus.desync.com:6969","udp://open.demonii.com:1337","udp://tracker.coppersurfer.tk:6969","udp://tracker.leechers-paradise.org:6969","udp://zer0day.ch:1337"],"urlList":[]}}