{"title":"The.Office.US.S02E15.1080p.HEVC.x265-MeGusta","magnet":"magnet:?xt=urn:btih:9ec32f927c2994387f6e2d893c6e1417bfc99ab3&dn=The.Office.US.S02E15.1080p.HEVC.x265-MeGusta&tr=udp%3A%2F%2Ftracker.leechers-paradise.org%3A6969&tr=udp%3A%2F%2Fzer0day.ch%3A1337&tr=udp%3A%2F%2Fopen.demonii.com%3A1337&tr=udp%3A%2F%2Ftracker.coppersurfer.tk%3A6969&tr=udp%3A%2F%2Fexodus.desync.com%3A6969","uploader":"TvTeam","categoryP":"video","categoryS":"tv_shows","size":"495384490","seeders":"2","leechers":"0","description":"Torrent is coming from:\r\n~~~~~~~~~~~~~~~~~~~~~~~~~~~~~\r\n <a href=\"\nhttps://torrenting.me\" rel=\"nofollow\" target=\"_NEW\">\nhttps://torrenting.me</a>\r\n\r\n~~~~~~~~~~~~~~~~~~~~~~~~~~~~~\r\n\r\nJoin us and become part of the BIG family! Yarrrrrrrrrrrrrr!!!","last_updated":"2018-03-13T12:24:32.975Z","parsed":{"xt":"urn:btih:9ec32f927c2994387f6e2d893c6e1417bfc99ab3","dn":"The.Office.US.S02E15.1080p.HEVC.x265-MeGusta","tr":["udp://exodus.desync.com:6969","udp://open.demonii.com:1337","udp://tracker.coppersurfer.tk:6969","udp://tracker.leechers-paradise.org:6969","udp://zer0day.ch:1337"],"infoHash":"9ec32f927c2994387f6e2d893c6e1417bfc99ab3","infoHashBuffer":{"type":"Buffer","data":[158,195,47,146,124,41,148,56,127,110,45,137,60,110,20,23,191,201,154,179]},"name":"The.Office.US.S02E15.1080p.HEVC.x265-MeGusta","announce":["udp://exodus.desync.com:6969","udp://open.demonii.com:1337","udp://tracker.coppersurfer.tk:6969","udp://tracker.leechers-paradise.org:6969","udp://zer0day.ch:1337"],"urlList":[]}}