{"title":"The.Tesla.Files.S01E03.480p.x264-mSD[TGx]","magnet":"magnet:?xt=urn:btih:9f23d8092c0cc46c2cd6a01a52a0d0afc819e541&dn=The.Tesla.Files.S01E03.480p.x264-mSD%5BTGx%5D&tr=udp%3A%2F%2Ftracker.leechers-paradise.org%3A6969&tr=udp%3A%2F%2Fzer0day.ch%3A1337&tr=udp%3A%2F%2Fopen.demonii.com%3A1337&tr=udp%3A%2F%2Ftracker.coppersurfer.tk%3A6969&tr=udp%3A%2F%2Fexodus.desync.com%3A6969","uploader":"makintos13","categoryP":"video","categoryS":"tv_shows","size":"244494340","seeders":"26","leechers":"7","description":"The.Tesla.Files.S01E03.480p.x264-mSD[TGx]\n \n MEDIAINFO\n Container = Matroska (mkv)\n Duration = 00:41:58.615\n Filesize = 232 MiB\n --Video\n Codec info = AVC High@L3 | V_MPEG4/ISO/AVC\n Resolution = 640x480\n Display AR = 1.778 | 16:9\n Bitrate = 630 kb/s\n Framerate = VFR \n Color space = YUV\n Chroma subsampling = 4:2:0\n Encoder = x264 - core 152 r2851 ba24899\n --Audio\n Codec info = MPEG Audio Layer 3 | A_MPEG/L3\n Channels = 2\n Bitrate = CBR 128 kb/s\n Samplerate = 48.0 kHz\n Language = English\n \n SCREENS\n  <a href=\" https://imgmak.com/image/6EK\" rel=\"nofollow\" target=\"_NEW\"> https://imgmak.com/image/6EK</a>\n  <a href=\" https://imgmak.com/image/6ET\" rel=\"nofollow\" target=\"_NEW\"> https://imgmak.com/image/6ET</a>\n  <a href=\" https://imgmak.com/image/6Ea\" rel=\"nofollow\" target=\"_NEW\"> https://imgmak.com/image/6Ea</a>\n  <a href=\" https://imgmak.com/image/6Ep\" rel=\"nofollow\" target=\"_NEW\"> https://imgmak.com/image/6Ep</a>\n  <a href=\" https://imgmak.com/image/6ER\" rel=\"nofollow\" target=\"_NEW\"> https://imgmak.com/image/6ER</a>\n  <a href=\" https://imgmak.com/image/6Eb\" rel=\"nofollow\" target=\"_NEW\"> https://imgmak.com/image/6Eb</a>","last_updated":"2018-05-19T12:12:57.938Z","parsed":{"xt":"urn:btih:9f23d8092c0cc46c2cd6a01a52a0d0afc819e541","dn":"The.Tesla.Files.S01E03.480p.x264-mSD[TGx]","tr":["udp://exodus.desync.com:6969","udp://open.demonii.com:1337","udp://tracker.coppersurfer.tk:6969","udp://tracker.leechers-paradise.org:6969","udp://zer0day.ch:1337"],"infoHash":"9f23d8092c0cc46c2cd6a01a52a0d0afc819e541","infoHashBuffer":{"type":"Buffer","data":[159,35,216,9,44,12,196,108,44,214,160,26,82,160,208,175,200,25,229,65]},"name":"The.Tesla.Files.S01E03.480p.x264-mSD[TGx]","announce":["udp://exodus.desync.com:6969","udp://open.demonii.com:1337","udp://tracker.coppersurfer.tk:6969","udp://tracker.leechers-paradise.org:6969","udp://zer0day.ch:1337"],"urlList":[]}}