{"title":"Audrey Bitoni","magnet":"magnet:?xt=urn:btih:a6a237d5d677b7b531ca042e0ff704e6648adc60&dn=+Audrey+Bitoni&tr=udp%3A%2F%2Ftracker.leechers-paradise.org%3A6969&tr=udp%3A%2F%2Fzer0day.ch%3A1337&tr=udp%3A%2F%2Fopen.demonii.com%3A1337&tr=udp%3A%2F%2Ftracker.coppersurfer.tk%3A6969&tr=udp%3A%2F%2Fexodus.desync.com%3A6969","uploader":"adderiyk","categoryP":"porn","categoryS":"hd___movies","size":"1431946004","seeders":"11","leechers":"24","description":" <a href=\"http://imgsalem.com/img-5b35df8934982.html\" rel=\"nofollow\" target=\"_NEW\">http://imgsalem.com/img-5b35df8934982.html</a> <a href=\"\nhttp://imgsalem.com/img-5b35df8936192.html\" rel=\"nofollow\" target=\"_NEW\">\nhttp://imgsalem.com/img-5b35df8936192.html</a>","last_updated":"2018-06-29T12:08:17.787Z","parsed":{"xt":"urn:btih:a6a237d5d677b7b531ca042e0ff704e6648adc60","dn":" Audrey Bitoni","tr":["udp://exodus.desync.com:6969","udp://open.demonii.com:1337","udp://tracker.coppersurfer.tk:6969","udp://tracker.leechers-paradise.org:6969","udp://zer0day.ch:1337"],"infoHash":"a6a237d5d677b7b531ca042e0ff704e6648adc60","infoHashBuffer":{"type":"Buffer","data":[166,162,55,213,214,119,183,181,49,202,4,46,15,247,4,230,100,138,220,96]},"name":" Audrey Bitoni","announce":["udp://exodus.desync.com:6969","udp://open.demonii.com:1337","udp://tracker.coppersurfer.tk:6969","udp://tracker.leechers-paradise.org:6969","udp://zer0day.ch:1337"],"urlList":[]}}