{"title":"FL Studio Producer Edition 11.0.6+Plugins Bundle R2R6015","magnet":"magnet:?xt=urn:btih:a96248e2a3fd49cd4bd0adeb2e9085d08e396f9b&dn=FL+Studio+Producer+Edition+11.0.6%2BPlugins+Bundle+R2R6015&tr=udp%3A%2F%2Ftracker.leechers-paradise.org%3A6969&tr=udp%3A%2F%2Fzer0day.ch%3A1337&tr=udp%3A%2F%2Fopen.demonii.com%3A1337&tr=udp%3A%2F%2Ftracker.coppersurfer.tk%3A6969&tr=udp%3A%2F%2Fexodus.desync.com%3A6969","uploader":"fax_pro","categoryP":"applications","categoryS":"windows","size":"24697378","seeders":"517","leechers":"344","description":"================                     ================ \r\n$$$$$$$$$$$$$$$..({[INSTALL NOTES]}...$$$$$$$$$$$$$$$\r\n================                     ================ \r\n\r\n&gt;&gt;&gt;    ==&gt; Install the Program\r\n&gt;&gt;&gt;    ==&gt; Turn Of Internet [Wont Work Otherwise]\r\n&gt;&gt;&gt;    ==&gt; Use Given Kaspersky Reset Trial To Reset Trial Again\r\n \r\nTorrent is coming from:  <a href=\"\nhttps://torrenting.me\" rel=\"nofollow\" target=\"_NEW\">\nhttps://torrenting.me</a>\r\n.............................\r\n~~~~~~~~~~~~~~~~~~~~~~~~~~~~~\r\n\r\n&gt;&gt;&gt;     1) Unpack and install\r\n&gt;&gt;&gt;     2) Use the key generator to generate a valid serial\r\n&gt;&gt;&gt;     3) Enjoy this release!\r\n\r\n      100%   $$$ Don&apos;t Forget to buy the program.$$$  100%","last_updated":"2018-04-13T16:52:20.261Z","parsed":{"xt":"urn:btih:a96248e2a3fd49cd4bd0adeb2e9085d08e396f9b","dn":"FL Studio Producer Edition 11.0.6 Plugins Bundle R2R6015","tr":["udp://exodus.desync.com:6969","udp://open.demonii.com:1337","udp://tracker.coppersurfer.tk:6969","udp://tracker.leechers-paradise.org:6969","udp://zer0day.ch:1337"],"infoHash":"a96248e2a3fd49cd4bd0adeb2e9085d08e396f9b","infoHashBuffer":{"type":"Buffer","data":[169,98,72,226,163,253,73,205,75,208,173,235,46,144,133,208,142,57,111,155]},"name":"FL Studio Producer Edition 11.0.6 Plugins Bundle R2R6015","announce":["udp://exodus.desync.com:6969","udp://open.demonii.com:1337","udp://tracker.coppersurfer.tk:6969","udp://tracker.leechers-paradise.org:6969","udp://zer0day.ch:1337"],"urlList":[]}}