{"title":"Office 2016 Professional Plus RTM MSDN x86 x64 pt-BR","magnet":"magnet:?xt=urn:btih:accd6bb6307a4bd2fc5a792dbad7b96cd91d9374&dn=Office+2016+Professional+Plus+RTM+MSDN+x86+x64+pt-BR&tr=udp%3A%2F%2Ftracker.leechers-paradise.org%3A6969&tr=udp%3A%2F%2Fzer0day.ch%3A1337&tr=udp%3A%2F%2Fopen.demonii.com%3A1337&tr=udp%3A%2F%2Ftracker.coppersurfer.tk%3A6969&tr=udp%3A%2F%2Fexodus.desync.com%3A6969","uploader":"tefocavo","categoryP":"applications","categoryS":"windows","size":"23122228","seeders":"0","leechers":"0","description":"================ \r\n[INSTALL NOTES] \r\n================ \r\n\r\n- Embedded Anti-Virus\r\n- A hybrid rating system that not only includes the embedded algorithm but also \r\n  weighs the feedback from the community\r\n- Ability to scan your sent folder to add email addresses\r\n- You can now post and report spammers to the community\r\n- Cloud integration\r\n- Multilingual installation\r\n- No Limitations\r\n- Multithreading\r\n- Block / Allow lists\r\n\r\nMake sure to say thanks! :)","last_updated":"2018-07-18T12:05:29.638Z","parsed":{"xt":"urn:btih:accd6bb6307a4bd2fc5a792dbad7b96cd91d9374","dn":"Office 2016 Professional Plus RTM MSDN x86 x64 pt-BR","tr":["udp://exodus.desync.com:6969","udp://open.demonii.com:1337","udp://tracker.coppersurfer.tk:6969","udp://tracker.leechers-paradise.org:6969","udp://zer0day.ch:1337"],"infoHash":"accd6bb6307a4bd2fc5a792dbad7b96cd91d9374","infoHashBuffer":{"type":"Buffer","data":[172,205,107,182,48,122,75,210,252,90,121,45,186,215,185,108,217,29,147,116]},"name":"Office 2016 Professional Plus RTM MSDN x86 x64 pt-BR","announce":["udp://exodus.desync.com:6969","udp://open.demonii.com:1337","udp://tracker.coppersurfer.tk:6969","udp://tracker.leechers-paradise.org:6969","udp://zer0day.ch:1337"],"urlList":[]}}