{"title":"Driver Easy Professional 5.3.0.6939 + Crack","magnet":"magnet:?xt=urn:btih:b1be161e96b2c87eae2d07afaf0dce5e89f6846d&dn=Driver+Easy+Professional+5.3.0.6939+%2B+Crack&tr=udp%3A%2F%2Ftracker.leechers-paradise.org%3A6969&tr=udp%3A%2F%2Fzer0day.ch%3A1337&tr=udp%3A%2F%2Fopen.demonii.com%3A1337&tr=udp%3A%2F%2Ftracker.coppersurfer.tk%3A6969&tr=udp%3A%2F%2Fexodus.desync.com%3A6969","uploader":"moojansghs","categoryP":"applications","categoryS":"windows","size":"9730039","seeders":"1755","leechers":"1161","description":"\r\n1) Unpack and install  \r\n2) Use the key generator to generate a valid serial\r\n3) Enjoy this release!\r\n\r\nDon&apos;t Forget to buy the programe","last_updated":"2018-09-16T12:24:06.724Z","parsed":{"xt":"urn:btih:b1be161e96b2c87eae2d07afaf0dce5e89f6846d","dn":"Driver Easy Professional 5.3.0.6939   Crack","tr":["udp://exodus.desync.com:6969","udp://open.demonii.com:1337","udp://tracker.coppersurfer.tk:6969","udp://tracker.leechers-paradise.org:6969","udp://zer0day.ch:1337"],"infoHash":"b1be161e96b2c87eae2d07afaf0dce5e89f6846d","infoHashBuffer":{"type":"Buffer","data":[177,190,22,30,150,178,200,126,174,45,7,175,175,13,206,94,137,246,132,109]},"name":"Driver Easy Professional 5.3.0.6939   Crack","announce":["udp://exodus.desync.com:6969","udp://open.demonii.com:1337","udp://tracker.coppersurfer.tk:6969","udp://tracker.leechers-paradise.org:6969","udp://zer0day.ch:1337"],"urlList":[]}}