{"title":"Alien Skin Software Photo Bundle 3.0 2017 MacOs","magnet":"magnet:?xt=urn:btih:b7032c813ab0eb520b94022a46c5fb116eaf5097&dn=Alien+Skin+Software+Photo+Bundle+3.0+2017+MacOs&tr=udp%3A%2F%2Ftracker.leechers-paradise.org%3A6969&tr=udp%3A%2F%2Fzer0day.ch%3A1337&tr=udp%3A%2F%2Fopen.demonii.com%3A1337&tr=udp%3A%2F%2Ftracker.coppersurfer.tk%3A6969&tr=udp%3A%2F%2Fexodus.desync.com%3A6969","uploader":"Lite8Hge","categoryP":"applications","categoryS":"mac","size":"419229994","seeders":"0","leechers":"0","description":"MAC OS X Includes crack\r\n- macOS 10.12, OS X 10.11 and OS X 10.10, with the latest revision\r\n- Multicore Intel processor with 64-bit support\r\n- 4 logical cores or higher recommended\r\n- 2 GB RAM 8 GB RAM or higher recommended\r\n- 750 MB hard disk space for application files\r\n- Solid-state drive recommended\r\n- 1280 x 800 screen resolution 1920 x 1080 recommended\r\n- Mouse or tablet","last_updated":"2018-02-01T12:05:10.223Z","parsed":{"xt":"urn:btih:b7032c813ab0eb520b94022a46c5fb116eaf5097","dn":"Alien Skin Software Photo Bundle 3.0 2017 MacOs","tr":["udp://exodus.desync.com:6969","udp://open.demonii.com:1337","udp://tracker.coppersurfer.tk:6969","udp://tracker.leechers-paradise.org:6969","udp://zer0day.ch:1337"],"infoHash":"b7032c813ab0eb520b94022a46c5fb116eaf5097","infoHashBuffer":{"type":"Buffer","data":[183,3,44,129,58,176,235,82,11,148,2,42,70,197,251,17,110,175,80,151]},"name":"Alien Skin Software Photo Bundle 3.0 2017 MacOs","announce":["udp://exodus.desync.com:6969","udp://open.demonii.com:1337","udp://tracker.coppersurfer.tk:6969","udp://tracker.leechers-paradise.org:6969","udp://zer0day.ch:1337"],"urlList":[]}}