{"title":"Beyond The Edge 2018 Movies 720p BluRay x264 5.1 +Sample ☻rDX☻","magnet":"magnet:?xt=urn:btih:b8ce2c4b2495aa5a20ce026f155b68b6546a189a&dn=Beyond+The+Edge+2018+Movies+720p+BluRay+x264+5.1+%2BSample+%E2%98%BBrDX%E2%98%BB&tr=udp%3A%2F%2Ftracker.leechers-paradise.org%3A6969&tr=udp%3A%2F%2Fzer0day.ch%3A1337&tr=udp%3A%2F%2Fopen.demonii.com%3A1337&tr=udp%3A%2F%2Ftracker.coppersurfer.tk%3A6969&tr=udp%3A%2F%2Fexodus.desync.com%3A6969","uploader":"basicssom","categoryP":"video","categoryS":"hd___movies","size":"1136829688","seeders":"0","leechers":"0","description":"Beyond The Edge 2018 Movies 720p BluRay x264 5.1 with Sample &#x263B;rDX&#x263B;\r\n\r\nSCREEN SHOTS &amp; POSTER:\r\n   <a href=\"\nhttp://iphonehosting.eu/2018/4/loan/index.html\" rel=\"nofollow\" target=\"_NEW\">\nhttp://iphonehosting.eu/2018/4/loan/index.html</a> <a href=\"\nhttp://iphonehosting.eu/2018/4/loan/1.html\" rel=\"nofollow\" target=\"_NEW\">\nhttp://iphonehosting.eu/2018/4/loan/1.html</a> <a href=\"\nhttp://iphonehosting.eu/2018/4/loan/2.html\" rel=\"nofollow\" target=\"_NEW\">\nhttp://iphonehosting.eu/2018/4/loan/2.html</a>   <a href=\"\nhttp://iphonehosting.eu/2018/4/loan/3.html\" rel=\"nofollow\" target=\"_NEW\">\nhttp://iphonehosting.eu/2018/4/loan/3.html</a>   <a href=\"\nhttp://iphonehosting.eu/2018/4/loan/4.html\" rel=\"nofollow\" target=\"_NEW\">\nhttp://iphonehosting.eu/2018/4/loan/4.html</a>   <a href=\"\nhttp://iphonehosting.eu/2018/4/loan/5.html\" rel=\"nofollow\" target=\"_NEW\">\nhttp://iphonehosting.eu/2018/4/loan/5.html</a>   <a href=\"\nhttp://iphonehosting.eu/2018/4/loan/6.html\" rel=\"nofollow\" target=\"_NEW\">\nhttp://iphonehosting.eu/2018/4/loan/6.html</a>   <a href=\"\nhttp://iphonehosting.eu/2018/4/loan/7.html\" rel=\"nofollow\" target=\"_NEW\">\nhttp://iphonehosting.eu/2018/4/loan/7.html</a>   <a href=\"\nhttp://iphonehosting.eu/2018/4/loan/8.html\" rel=\"nofollow\" target=\"_NEW\">\nhttp://iphonehosting.eu/2018/4/loan/8.html</a>   <a href=\"\nhttp://iphonehosting.eu/2018/4/loan/9.html\" rel=\"nofollow\" target=\"_NEW\">\nhttp://iphonehosting.eu/2018/4/loan/9.html</a>   <a href=\"\nhttp://iphonehosting.eu/2018/4/loan/10.html\" rel=\"nofollow\" target=\"_NEW\">\nhttp://iphonehosting.eu/2018/4/loan/10.html</a>","last_updated":"2018-04-09T12:10:07.376Z","parsed":{"xt":"urn:btih:b8ce2c4b2495aa5a20ce026f155b68b6546a189a","dn":"Beyond The Edge 2018 Movies 720p BluRay x264 5.1  Sample ☻rDX☻","tr":["udp://exodus.desync.com:6969","udp://open.demonii.com:1337","udp://tracker.coppersurfer.tk:6969","udp://tracker.leechers-paradise.org:6969","udp://zer0day.ch:1337"],"infoHash":"b8ce2c4b2495aa5a20ce026f155b68b6546a189a","infoHashBuffer":{"type":"Buffer","data":[184,206,44,75,36,149,170,90,32,206,2,111,21,91,104,182,84,106,24,154]},"name":"Beyond The Edge 2018 Movies 720p BluRay x264 5.1  Sample ☻rDX☻","announce":["udp://exodus.desync.com:6969","udp://open.demonii.com:1337","udp://tracker.coppersurfer.tk:6969","udp://tracker.leechers-paradise.org:6969","udp://zer0day.ch:1337"],"urlList":[]}}