{"title":"The.Hobbit.3-The.Battle.of.The.Five.Armies.2013.Extended.Bluray1","magnet":"magnet:?xt=urn:btih:b930e56fcf5ecaf5c32a233563cfe47cc88d9ed6&dn=The.Hobbit.3-The.Battle.of.The.Five.Armies.2013.Extended.Bluray1&tr=udp%3A%2F%2Ftracker.leechers-paradise.org%3A6969&tr=udp%3A%2F%2Fzer0day.ch%3A1337&tr=udp%3A%2F%2Fopen.demonii.com%3A1337&tr=udp%3A%2F%2Ftracker.coppersurfer.tk%3A6969&tr=udp%3A%2F%2Fexodus.desync.com%3A6969","uploader":"SaM","categoryP":"video","categoryS":"hd___movies","size":"18808840187","seeders":"0","leechers":"0","description":"The.Hobbit.3-The.Battle.of.The.Five.Armies.2013.Extended.Bluray1080p.x264.DTS-HDMA.7.1[En+Hi]-DTOne\r\n\r <a href=\" https://www.ettv.be/home/\" rel=\"nofollow\" target=\"_NEW\"> https://www.ettv.be/home/</a>\r\n <a href=\"\nhttps://extraimage.net/image/7jMo\" rel=\"nofollow\" target=\"_NEW\">\nhttps://extraimage.net/image/7jMo</a> <a href=\"\nhttps://extraimage.net/image/7jMk\" rel=\"nofollow\" target=\"_NEW\">\nhttps://extraimage.net/image/7jMk</a> <a href=\"\nhttps://extraimage.net/image/7jMH\" rel=\"nofollow\" target=\"_NEW\">\nhttps://extraimage.net/image/7jMH</a> <a href=\"\nhttps://extraimage.net/image/7jMF\" rel=\"nofollow\" target=\"_NEW\">\nhttps://extraimage.net/image/7jMF</a> <a href=\"\nhttps://extraimage.net/image/7jMD\" rel=\"nofollow\" target=\"_NEW\">\nhttps://extraimage.net/image/7jMD</a> <a href=\"\nhttps://extraimage.net/image/7jM5\" rel=\"nofollow\" target=\"_NEW\">\nhttps://extraimage.net/image/7jM5</a> <a href=\"\nhttps://extraimage.net/image/7jMg\" rel=\"nofollow\" target=\"_NEW\">\nhttps://extraimage.net/image/7jMg</a> <a href=\"\nhttps://extraimage.net/image/7jMX\" rel=\"nofollow\" target=\"_NEW\">\nhttps://extraimage.net/image/7jMX</a> <a href=\"\nhttps://extraimage.net/image/7jMP\" rel=\"nofollow\" target=\"_NEW\">\nhttps://extraimage.net/image/7jMP</a> <a href=\"\nhttps://extraimage.net/image/7jMG\" rel=\"nofollow\" target=\"_NEW\">\nhttps://extraimage.net/image/7jMG</a> <a href=\"\nhttps://extraimage.net/image/7jMr\" rel=\"nofollow\" target=\"_NEW\">\nhttps://extraimage.net/image/7jMr</a> <a href=\"\nhttps://extraimage.net/image/7jMp\" rel=\"nofollow\" target=\"_NEW\">\nhttps://extraimage.net/image/7jMp</a> <a href=\"\nhttps://extraimage.net/image/7jMY\" rel=\"nofollow\" target=\"_NEW\">\nhttps://extraimage.net/image/7jMY</a>\r\n\r\nSPECS\r\n\r\nSource : FHD Bluray\r\n\r\nFormat : Matroska\r\nFile size : 17.5 GiB\r\nDuration : 2 h 44 min\r\nOverall bit rate : 15.2 Mb/s\r\n\r\nVideo\r\nFormat : AVC/x264\r\nBit rate : 10 000 kb/s\r\nWidth : 1 920 pixels\r\nHeight : 800 pixels\r\n\r\nAudio\r\nAudio #1\r\nFormat : DTS-HDMA\r\nBit rate : 4 764 kb/s / 1 509 kb/s\r\nChannel(s) : 8 channels / 6 channels\r\nBit depth : 24 bits\r\nLanguage : English\r\n\r\n\r\nAudio #2\r\nFormat : AC-3\r\nBit rate : 448 kb/s\r\nChannel(s) : 6 channels\r\nLanguage : Hindi\r\n\r\n\r\n\r\nSubtitles\r\nEnglish French\r\n\r\nChapters : Yes\r\nSample Included\r\n\r\nRipped by: MikeKhan","last_updated":"2018-09-10T12:01:41.571Z","parsed":{"xt":"urn:btih:b930e56fcf5ecaf5c32a233563cfe47cc88d9ed6","dn":"The.Hobbit.3-The.Battle.of.The.Five.Armies.2013.Extended.Bluray1","tr":["udp://exodus.desync.com:6969","udp://open.demonii.com:1337","udp://tracker.coppersurfer.tk:6969","udp://tracker.leechers-paradise.org:6969","udp://zer0day.ch:1337"],"infoHash":"b930e56fcf5ecaf5c32a233563cfe47cc88d9ed6","infoHashBuffer":{"type":"Buffer","data":[185,48,229,111,207,94,202,245,195,42,35,53,99,207,228,124,200,141,158,214]},"name":"The.Hobbit.3-The.Battle.of.The.Five.Armies.2013.Extended.Bluray1","announce":["udp://exodus.desync.com:6969","udp://open.demonii.com:1337","udp://tracker.coppersurfer.tk:6969","udp://tracker.leechers-paradise.org:6969","udp://zer0day.ch:1337"],"urlList":[]}}