{"title":"The Great Crash of 1929 by John Kenneth Galbraith EPUB","magnet":"magnet:?xt=urn:btih:c91eae009e86a8a48094728183a4f234d2880ac4&dn=The+Great+Crash+of+1929+by+John+Kenneth+Galbraith+EPUB&tr=udp%3A%2F%2Ftracker.leechers-paradise.org%3A6969&tr=udp%3A%2F%2Fzer0day.ch%3A1337&tr=udp%3A%2F%2Fopen.demonii.com%3A1337&tr=udp%3A%2F%2Ftracker.coppersurfer.tk%3A6969&tr=udp%3A%2F%2Fexodus.desync.com%3A6969","uploader":"zakareya","categoryP":"other","categoryS":"e_books","size":"260328","seeders":"0","leechers":"0","description":"xx\r\n\r\nThe Great Crash of 1929 by John Kenneth Galbraith EPUB\r\n\r\nWith grace and wit, America&apos;s foremost economist examines the boom-and-bust that led to the stock market crash of 1929. Economic writings are rarely notable for their entertainment value, but this widely admired best-seller is the exception. Galbraith&apos;s light touch makes his expert analysis of America&apos;s greatest financial disaster a surprisingly engaging read for anyone.\r\n\r\nxx","last_updated":"2018-05-17T12:02:25.808Z","parsed":{"xt":"urn:btih:c91eae009e86a8a48094728183a4f234d2880ac4","dn":"The Great Crash of 1929 by John Kenneth Galbraith EPUB","tr":["udp://exodus.desync.com:6969","udp://open.demonii.com:1337","udp://tracker.coppersurfer.tk:6969","udp://tracker.leechers-paradise.org:6969","udp://zer0day.ch:1337"],"infoHash":"c91eae009e86a8a48094728183a4f234d2880ac4","infoHashBuffer":{"type":"Buffer","data":[201,30,174,0,158,134,168,164,128,148,114,129,131,164,242,52,210,136,10,196]},"name":"The Great Crash of 1929 by John Kenneth Galbraith EPUB","announce":["udp://exodus.desync.com:6969","udp://open.demonii.com:1337","udp://tracker.coppersurfer.tk:6969","udp://tracker.leechers-paradise.org:6969","udp://zer0day.ch:1337"],"urlList":[]}}