{"title":"HEYZO_1754 Rei Kitajima  JAV UNCENSORED","magnet":"magnet:?xt=urn:btih:c9df1c3dbdc2e9b160e9aed534799b20531ed0b4&dn=HEYZO_1754+Rei+Kitajima++JAV+UNCENSORED&tr=udp%3A%2F%2Ftracker.leechers-paradise.org%3A6969&tr=udp%3A%2F%2Fzer0day.ch%3A1337&tr=udp%3A%2F%2Fopen.demonii.com%3A1337&tr=udp%3A%2F%2Ftracker.coppersurfer.tk%3A6969&tr=udp%3A%2F%2Fexodus.desync.com%3A6969","uploader":"3xplanet","categoryP":"porn","categoryS":"hd___movies","size":"2377312738","seeders":"56","leechers":"79","description":"cover <a href=\"\nhttp://3xplanet.com/view/338403.html\" rel=\"nofollow\" target=\"_NEW\">\nhttp://3xplanet.com/view/338403.html</a>\r\nscreens <a href=\"\nhttp://3xplanet.com/view/338475.html\" rel=\"nofollow\" target=\"_NEW\">\nhttp://3xplanet.com/view/338475.html</a>\r\nStarring: Rei Kitajima \r\nStudio: Heyzo","last_updated":"2018-06-17T12:03:05.644Z","parsed":{"xt":"urn:btih:c9df1c3dbdc2e9b160e9aed534799b20531ed0b4","dn":"HEYZO_1754 Rei Kitajima  JAV UNCENSORED","tr":["udp://exodus.desync.com:6969","udp://open.demonii.com:1337","udp://tracker.coppersurfer.tk:6969","udp://tracker.leechers-paradise.org:6969","udp://zer0day.ch:1337"],"infoHash":"c9df1c3dbdc2e9b160e9aed534799b20531ed0b4","infoHashBuffer":{"type":"Buffer","data":[201,223,28,61,189,194,233,177,96,233,174,213,52,121,155,32,83,30,208,180]},"name":"HEYZO_1754 Rei Kitajima  JAV UNCENSORED","announce":["udp://exodus.desync.com:6969","udp://open.demonii.com:1337","udp://tracker.coppersurfer.tk:6969","udp://tracker.leechers-paradise.org:6969","udp://zer0day.ch:1337"],"urlList":[]}}