{"title":"PornMegaLoad.18.05.14.Peaches.Larue.Wide.Load.Nympho.XXX.1080...","magnet":"magnet:?xt=urn:btih:d09b7a2c8597c5a9d414f6e691fe90189f16d954&dn=PornMegaLoad.18.05.14.Peaches.Larue.Wide.Load.Nympho.XXX.1080...&tr=udp%3A%2F%2Ftracker.leechers-paradise.org%3A6969&tr=udp%3A%2F%2Fzer0day.ch%3A1337&tr=udp%3A%2F%2Fopen.demonii.com%3A1337&tr=udp%3A%2F%2Ftracker.coppersurfer.tk%3A6969&tr=udp%3A%2F%2Fexodus.desync.com%3A6969","uploader":"juggs99","categoryP":"porn","categoryS":"hd___movies","size":"1235578170","seeders":"7","leechers":"13","description":"\nPornMegaLoad.18.05.14.Peaches.Larue.Wide.Load.Nympho.XXX.1080p.MP4-KTR \r\n\n\n[Format]:    MPEG-4\n[Duration]:    20mn 17s\n[Resolution]:  1 920 x 1 080 pixels\n[Display aspect ratio]:    16:9\n[Frame rate mode]:    Constant\n[Frame rate]:    29.970 fps\n\r\n\n#N1C -&gt; To avoid fakes, ALWAYS check that the torrent was added by NO1CARES\r\n\n\r\n\n\nHelp us by donating with Bitcoin: 1Pgwp16gmLHmPzgjJLxZnMw7YeqiUekUoe\r\n\nScreens...\r <a href=\"\nhttps://www.xxximagetpb.org/image/SmoWOP\" rel=\"nofollow\" target=\"_NEW\">\nhttps://www.xxximagetpb.org/image/SmoWOP</a>\r <a href=\"\nhttps://www.xxximagetpb.org/image/SmoZ27\" rel=\"nofollow\" target=\"_NEW\">\nhttps://www.xxximagetpb.org/image/SmoZ27</a>\r <a href=\"\nhttps://www.xxximagetpb.org/image/Smotkb\" rel=\"nofollow\" target=\"_NEW\">\nhttps://www.xxximagetpb.org/image/Smotkb</a>\r <a href=\"\nhttps://www.xxximagetpb.org/image/SmoHEh\" rel=\"nofollow\" target=\"_NEW\">\nhttps://www.xxximagetpb.org/image/SmoHEh</a>","last_updated":"2018-05-15T12:10:46.063Z","parsed":{"xt":"urn:btih:d09b7a2c8597c5a9d414f6e691fe90189f16d954","dn":"PornMegaLoad.18.05.14.Peaches.Larue.Wide.Load.Nympho.XXX.1080...","tr":["udp://exodus.desync.com:6969","udp://open.demonii.com:1337","udp://tracker.coppersurfer.tk:6969","udp://tracker.leechers-paradise.org:6969","udp://zer0day.ch:1337"],"infoHash":"d09b7a2c8597c5a9d414f6e691fe90189f16d954","infoHashBuffer":{"type":"Buffer","data":[208,155,122,44,133,151,197,169,212,20,246,230,145,254,144,24,159,22,217,84]},"name":"PornMegaLoad.18.05.14.Peaches.Larue.Wide.Load.Nympho.XXX.1080...","announce":["udp://exodus.desync.com:6969","udp://open.demonii.com:1337","udp://tracker.coppersurfer.tk:6969","udp://tracker.leechers-paradise.org:6969","udp://zer0day.ch:1337"],"urlList":[]}}