{"title":"[BabyGotBoobs/ Brazzers] Giselle Palmer - Ribbon Fucking [2018-0","magnet":"magnet:?xt=urn:btih:d1202ef59a4d151e7b4e2881b65bac1a360dc2aa&dn=%5BBabyGotBoobs%2F+Brazzers%5D+Giselle+Palmer+-+Ribbon+Fucking+%5B2018-0&tr=udp%3A%2F%2Ftracker.leechers-paradise.org%3A6969&tr=udp%3A%2F%2Fzer0day.ch%3A1337&tr=udp%3A%2F%2Fopen.demonii.com%3A1337&tr=udp%3A%2F%2Ftracker.coppersurfer.tk%3A6969&tr=udp%3A%2F%2Fexodus.desync.com%3A6969","uploader":"s3xpro","categoryP":"porn","categoryS":"hd___movies","size":"1371100085","seeders":"6","leechers":"12","description":"[BabyGotBoobs/ Brazzers] Giselle Palmer - Ribbon Fucking [2018-09-12, Big Tits, Blonde, Bondage, Deep Throat, Natural Tits, Straight, Tattoos, Titfuck, Cum In Mouth, 1080p]\r\n <a href=\"\nhttps://muskaer.com/image/8Bbit\" rel=\"nofollow\" target=\"_NEW\">\nhttps://muskaer.com/image/8Bbit</a>\r\n <a href=\"\nhttps://muskaer.com/image/8Bp6a\" rel=\"nofollow\" target=\"_NEW\">\nhttps://muskaer.com/image/8Bp6a</a>\r\n <a href=\"\nhttps://muskaer.com/image/8Bwtf\" rel=\"nofollow\" target=\"_NEW\">\nhttps://muskaer.com/image/8Bwtf</a>","last_updated":"2018-09-12T12:09:34.634Z","parsed":{"xt":"urn:btih:d1202ef59a4d151e7b4e2881b65bac1a360dc2aa","dn":"[BabyGotBoobs/ Brazzers] Giselle Palmer - Ribbon Fucking [2018-0","tr":["udp://exodus.desync.com:6969","udp://open.demonii.com:1337","udp://tracker.coppersurfer.tk:6969","udp://tracker.leechers-paradise.org:6969","udp://zer0day.ch:1337"],"infoHash":"d1202ef59a4d151e7b4e2881b65bac1a360dc2aa","infoHashBuffer":{"type":"Buffer","data":[209,32,46,245,154,77,21,30,123,78,40,129,182,91,172,26,54,13,194,170]},"name":"[BabyGotBoobs/ Brazzers] Giselle Palmer - Ribbon Fucking [2018-0","announce":["udp://exodus.desync.com:6969","udp://open.demonii.com:1337","udp://tracker.coppersurfer.tk:6969","udp://tracker.leechers-paradise.org:6969","udp://zer0day.ch:1337"],"urlList":[]}}