{"title":"Voice from the Void (4701-4800)","magnet":"magnet:?xt=urn:btih:d5eb85ce15c37fd3ee38efa05df218048913a50a&dn=Voice+from+the+Void+%284701-4800%29&tr=udp%3A%2F%2Ftracker.leechers-paradise.org%3A6969&tr=udp%3A%2F%2Fzer0day.ch%3A1337&tr=udp%3A%2F%2Fopen.demonii.com%3A1337&tr=udp%3A%2F%2Ftracker.coppersurfer.tk%3A6969&tr=udp%3A%2F%2Fexodus.desync.com%3A6969","uploader":"seering","categoryP":"other","categoryS":"other","size":"1979628","seeders":"0","leechers":"0","description":"Love them or hate them\r\nHere&apos;s something to chew\r\nQuestion the dichotomy\r\nChallenge your worldview","last_updated":"2018-11-15T13:25:25.320Z","parsed":{"xt":"urn:btih:d5eb85ce15c37fd3ee38efa05df218048913a50a","dn":"Voice from the Void (4701-4800)","tr":["udp://exodus.desync.com:6969","udp://open.demonii.com:1337","udp://tracker.coppersurfer.tk:6969","udp://tracker.leechers-paradise.org:6969","udp://zer0day.ch:1337"],"infoHash":"d5eb85ce15c37fd3ee38efa05df218048913a50a","infoHashBuffer":{"type":"Buffer","data":[213,235,133,206,21,195,127,211,238,56,239,160,93,242,24,4,137,19,165,10]},"name":"Voice from the Void (4701-4800)","announce":["udp://exodus.desync.com:6969","udp://open.demonii.com:1337","udp://tracker.coppersurfer.tk:6969","udp://tracker.leechers-paradise.org:6969","udp://zer0day.ch:1337"],"urlList":[]}}