{"title":"Remy.and.Papoose.Meet.the.Mackies.S01E03.720p.WEB.x264-TBS","magnet":"magnet:?xt=urn:btih:e492462d9de26f5f85c9050fc270ae2e570cdf22&dn=Remy.and.Papoose.Meet.the.Mackies.S01E03.720p.WEB.x264-TBS&tr=udp%3A%2F%2Ftracker.leechers-paradise.org%3A6969&tr=udp%3A%2F%2Fzer0day.ch%3A1337&tr=udp%3A%2F%2Fopen.demonii.com%3A1337&tr=udp%3A%2F%2Ftracker.coppersurfer.tk%3A6969&tr=udp%3A%2F%2Fexodus.desync.com%3A6969","uploader":"Supernova","categoryP":"video","categoryS":"hd___tv_shows","size":"874404301","seeders":"1","leechers":"1","description":"\nRemy.and.Papoose.Meet.the.Mackies.S01E03.720p.WEB.x264-TBS\n\n10/16/2018","last_updated":"2018-10-16T12:11:23.438Z","parsed":{"xt":"urn:btih:e492462d9de26f5f85c9050fc270ae2e570cdf22","dn":"Remy.and.Papoose.Meet.the.Mackies.S01E03.720p.WEB.x264-TBS","tr":["udp://exodus.desync.com:6969","udp://open.demonii.com:1337","udp://tracker.coppersurfer.tk:6969","udp://tracker.leechers-paradise.org:6969","udp://zer0day.ch:1337"],"infoHash":"e492462d9de26f5f85c9050fc270ae2e570cdf22","infoHashBuffer":{"type":"Buffer","data":[228,146,70,45,157,226,111,95,133,201,5,15,194,112,174,46,87,12,223,34]},"name":"Remy.and.Papoose.Meet.the.Mackies.S01E03.720p.WEB.x264-TBS","announce":["udp://exodus.desync.com:6969","udp://open.demonii.com:1337","udp://tracker.coppersurfer.tk:6969","udp://tracker.leechers-paradise.org:6969","udp://zer0day.ch:1337"],"urlList":[]}}